pyxmenu/__init__.py
pyxmenu/item/__init__.py
pyxmenu/item/divider.py
pyxmenu/item/attribute/__base__.py
pyxmenu/item/attribute/__init__.py
pyxmenu/item/attribute/alternative.py
pyxmenu/item/attribute/ansi.py
pyxmenu/item/attribute/color.py
pyxmenu/item/attribute/disabled.py
pyxmenu/item/attribute/dropdown.py
pyxmenu/item/attribute/emojize.py
pyxmenu/item/attribute/font.py
pyxmenu/item/attribute/href.py
pyxmenu/item/attribute/image.py
pyxmenu/item/attribute/key.py
pyxmenu/item/attribute/length.py
pyxmenu/item/attribute/parmas.py
pyxmenu/item/attribute/refresh.py
pyxmenu/item/attribute/shell.py
pyxmenu/item/attribute/size.py
pyxmenu/item/attribute/template_image.py
pyxmenu/item/attribute/terminal.py
pyxmenu/item/attribute/trim.py
pyxmenu/plugin/__init__.py
pyxmenu/section/__init__.py
pyxmenu-0.0.1.dist-info/METADATA
pyxmenu-0.0.1.dist-info/WHEEL
pyxmenu-0.0.1.dist-info/licenses/LICENSE
pyxmenu-0.0.1.dist-info/RECORD
